LICENSE
odd_collector_sdk/__init__.py
odd_collector_sdk/__version__.py
odd_collector_sdk/api/__init__.py
odd_collector_sdk/api/datasource_api.py
odd_collector_sdk/collector.py
odd_collector_sdk/domain/__init__.py
odd_collector_sdk/domain/adapter.py
odd_collector_sdk/domain/collector_config.py
odd_collector_sdk/domain/collector_config_loader.py
odd_collector_sdk/domain/filter.py
odd_collector_sdk/domain/plugin.py
odd_collector_sdk/errors.py
odd_collector_sdk/grammar_parser/__init__.py
odd_collector_sdk/grammar_parser/build_dataset_field.py
odd_collector_sdk/grammar_parser/exceptions.py
odd_collector_sdk/grammar_parser/field_types.py
odd_collector_sdk/job.py
odd_collector_sdk/load_adapter.py
odd_collector_sdk/logger.py
odd_collector_sdk/secrets/aws/ssm_parameter_store.py
odd_collector_sdk/secrets/base_secrets.py
odd_collector_sdk/secrets/secrets_backend_factory.py
odd_collector_sdk/shutdown.py
odd_collector_sdk/types/__init__.py
odd_collector_sdk/utils/__init__.py
odd_collector_sdk/utils/decorators.py
odd_collector_sdk/utils/json_encoder.py
odd_collector_sdk/utils/metadata.py
odd_collector_sdk/utils/print_version.py
odd_collector_sdk/utils/yaml_parser.py
odd_collector_sdk-0.3.60.dist-info/LICENSE
odd_collector_sdk-0.3.60.dist-info/METADATA
odd_collector_sdk-0.3.60.dist-info/WHEEL
odd_collector_sdk-0.3.60.dist-info/RECORD
