Metadata-Version: 2.1
Name: odd-collector-sdk
Version: 0.3.60
Summary: ODD Collector
Home-page: https://github.com/opendatadiscovery/odd-collector-sdk
License: Apache-2.0
Keywords: odd-collector-sdk,odd_collector_sdk,opendatadiscovery
Author: Open Data Discovery
Author-email: pypi@opendatadiscovery.org
Requires-Python: >=3.9,<4.0
Classifier: License :: OSI Approved :: Apache Software License
Classifier: Programming Language :: Python :: 3
Classifier: Programming Language :: Python :: 3.9
Classifier: Programming Language :: Python :: 3.10
Classifier: Programming Language :: Python :: 3.11
Requires-Dist: APScheduler (>=3.8.1,<4.0.0)
Requires-Dist: aiohttp (>=3.8.1,<4.0.0)
Requires-Dist: boto3 (>=1.34.88,<2.0.0)
Requires-Dist: botocore (>=1.34.88,<2.0.0)
Requires-Dist: flatdict (>=4.0.1,<5.0.0)
Requires-Dist: funcy (>=2.0,<3.0)
Requires-Dist: importlib-metadata (==6.11.0)
Requires-Dist: lark-parser (>=0.12.0,<0.13.0)
Requires-Dist: loguru (>=0.7.2,<0.8.0)
Requires-Dist: odd-models (>=2.0.47,<3.0.0)
Requires-Dist: oddrn-generator (>=0.1.101,<0.2.0)
Requires-Dist: prettytable (>=3.8.0,<4.0.0)
Requires-Dist: pyaml-env (>=1.1.5,<2.0.0)
Requires-Dist: pydantic (>=2.7.1,<3.0.0)
Requires-Dist: tqdm (>=4.64.1,<5.0.0)
Project-URL: Repository, https://github.com/opendatadiscovery/odd-collector-sdk
